TOPSIS_Mayank_102103037/__init__.py
TOPSIS_Mayank_102103037/main.py
topsis_3037-1.0.1.dist-info/LICENSE
topsis_3037-1.0.1.dist-info/METADATA
topsis_3037-1.0.1.dist-info/WHEEL
topsis_3037-1.0.1.dist-info/top_level.txt
topsis_3037-1.0.1.dist-info/RECORD
