Metadata-Version: 2.1
Name: topsis-3037
Version: 1.0.1
Summary: A topsis package for MCDM
Home-page: https://github.com/mayankzach/topsis
Author: Mayank
Author-email: Mayank@gmail.com
Project-URL: Bug Tracker, https://github.com/mayankzach/topsis
Classifier: Programming Language :: Python :: 3
Classifier: License :: OSI Approved :: MIT License
Classifier: Operating System :: OS Independent
Requires-Python: >=3.6
License-File: LICENSE
